validacion_terrenos/__init__.py
validacion_terrenos/terrenos_sahagun.py
validacion_terrenos-0.2.0.dist-info/METADATA
validacion_terrenos-0.2.0.dist-info/WHEEL
validacion_terrenos-0.2.0.dist-info/entry_points.txt
validacion_terrenos-0.2.0.dist-info/top_level.txt
validacion_terrenos-0.2.0.dist-info/RECORD
