Metadata-Version: 2.1
Name: validacion_terrenos
Version: 0.2.0
Summary: Validacion atributos terrenos
Home-page: https://github.com/tu_usuario/validacion_terrenos
Author: Daniel Vanegas
Author-email: tu_email@example.com
Classifier: Programming Language :: Python :: 3
Classifier: License :: OSI Approved :: MIT License
Classifier: Operating System :: OS Independent
Requires-Python: >=3.6
